indigopy/__init__.py
indigopy/core.py
indigopy/sample_data.pkl
tests/__init__.py
tests/test_core.py
indigopy_sriram_lab-1.1.0.dist-info/LICENSE
indigopy_sriram_lab-1.1.0.dist-info/METADATA
indigopy_sriram_lab-1.1.0.dist-info/WHEEL
indigopy_sriram_lab-1.1.0.dist-info/top_level.txt
indigopy_sriram_lab-1.1.0.dist-info/RECORD
