Metadata-Version: 2.1
Name: indigopy-sriram-lab
Version: 1.1.0
Summary: The Python implementation of INDIGO
Home-page: https://github.com/sriram-lab/INDIGOpy
Author: Chandrasekaran Lab
Author-email: csriram@umich.edu
License: UNKNOWN
Project-URL: Bug Reports, https://github.com/sriram-lab/INDIGOpy/issues
Project-URL: Source, https://github.com/sriram-lab/INDIGOpy/
Project-URL: Lab Website, https://systemsbiologylab.org/
Keywords: INDIGO,machine learning,combination therapy
Platform: UNKNOWN
Classifier: Programming Language :: Python :: 3.8
Classifier: Programming Language :: Python :: 3.9
Classifier: Programming Language :: Python :: 3.10
Requires-Python: >=3.8, <4
License-File: LICENSE
Requires-Dist: numpy
Requires-Dist: pandas
Requires-Dist: tqdm
